{
	"ExperimentId": "abea56e0cdb841b597321e6fe9086956.f-id.eda19542fc0f4b5a93b5e26555fc4d3c",
	"RunId": null,
	"ParentExperimentId": "abea56e0cdb841b597321e6fe9086956.s-id.eda19542fc0f4b5a93b5e26555fc4d3c.9951-03-05t01.45.47",
	"OriginalExperimentDocumentationLink": null,
	"Summary": "Logistic and Neural Network Classification",
	"Description": "Classification",
	"Graph": {
		"ModuleNodes": [{
				"Id": "d70d4b2c-a5fa-42a5-b8dd-dd13243f0ea3-133",
				"ModuleId": "506153734175476c4f62416c57734963.70530644c97a4ab685f788bf30a8be5f.v1-default-1716",
				"Comment": "75% for training (left)\n25% for scoring (right)",
				"CommentCollapsed": false,
				"Language": "DotNet",
				"Version": "4.5.0",
				"UsePreviousResults": false,
				"ModuleParameters": [{
						"ValueType": "Literal",
						"LinkedGlobalParameter": null,
						"Name": "Splitting mode",
						"Value": "Split Rows"
					}, {
						"ValueType": "Literal",
						"LinkedGlobalParameter": null,
						"Name": "Fraction of rows in the first output dataset",
						"Value": "0.75"
					}, {
						"ValueType": "Literal",
						"LinkedGlobalParameter": null,
						"Name": "Randomized split",
						"Value": "True"
					}, {
						"ValueType": "Literal",
						"LinkedGlobalParameter": null,
						"Name": "Random seed",
						"Value": "0"
					}, {
						"ValueType": "Literal",
						"LinkedGlobalParameter": null,
						"Name": "Stratified split",
						"Value": "False"
					}
				],
				"IsPartOfPartialRun": false,
				"InputPortsInternal": [{
						"Name": "Dataset",
						"DataSourceId": "abea56e0cdb841b597321e6fe9086956.1e96e0d6676f455db94755d700605ae9.v1-default-5",
						"TrainedModelId": null,
						"TransformModuleId": null,
						"Language": "DotNet",
						"Version": "4.5.0",
						"PortIndex": null,
						"NodeId": "d70d4b2c-a5fa-42a5-b8dd-dd13243f0ea3-133"
					}
				],
				"OutputPortsInternal": [{
						"Name": "Results dataset1",
						"NodeId": "d70d4b2c-a5fa-42a5-b8dd-dd13243f0ea3-133",
						"OutputType": null
					}, {
						"Name": "Results dataset2",
						"NodeId": "d70d4b2c-a5fa-42a5-b8dd-dd13243f0ea3-133",
						"OutputType": null
					}
				]
			}, {
				"Id": "d70d4b2c-a5fa-42a5-b8dd-dd13243f0ea3-170",
				"ModuleId": "506153734175476c4f62416c57734963.5cc7053eaa30450d96c0dae4be720977.v1-default-1562",
				"Comment": "",
				"CommentCollapsed": true,
				"Language": "DotNet",
				"Version": "4.5.0",
				"UsePreviousResults": false,
				"ModuleParameters": [{
						"ValueType": "Literal",
						"LinkedGlobalParameter": null,
						"Name": "Label column",
						"Value": "%7B%22isFilter%22%3Atrue%2C%22rules%22%3A%5B%7B%22ruleType%22%3A%22ColumnNames%22%2C%22columns%22%3A%5B%22ARR_DELAY%22%5D%2C%22exclude%22%3Afalse%7D%5D%2C%22ui%22%3A%7B%22withRules%22%3Atrue%7D%7D"
					}
				],
				"IsPartOfPartialRun": false,
				"InputPortsInternal": [{
						"Name": "Untrained model",
						"DataSourceId": null,
						"TrainedModelId": null,
						"TransformModuleId": null,
						"Language": "DotNet",
						"Version": "4.5.0",
						"PortIndex": null,
						"NodeId": "d70d4b2c-a5fa-42a5-b8dd-dd13243f0ea3-170"
					}, {
						"Name": "Dataset",
						"DataSourceId": null,
						"TrainedModelId": null,
						"TransformModuleId": null,
						"Language": "DotNet",
						"Version": "4.5.0",
						"PortIndex": null,
						"NodeId": "d70d4b2c-a5fa-42a5-b8dd-dd13243f0ea3-170"
					}
				],
				"OutputPortsInternal": [{
						"Name": "Trained model",
						"NodeId": "d70d4b2c-a5fa-42a5-b8dd-dd13243f0ea3-170",
						"OutputType": null
					}
				]
			}, {
				"Id": "d70d4b2c-a5fa-42a5-b8dd-dd13243f0ea3-175",
				"ModuleId": "506153734175476c4f62416c57734963.401b4f92e7244d5abe81d5b0ff9bdb33.v1-default-1730",
				"Comment": "",
				"CommentCollapsed": true,
				"Language": "DotNet",
				"Version": "4.5.0",
				"UsePreviousResults": false,
				"ModuleParameters": [{
						"ValueType": "Literal",
						"LinkedGlobalParameter": null,
						"Name": "Append score columns to output",
						"Value": "True"
					}
				],
				"IsPartOfPartialRun": false,
				"InputPortsInternal": [{
						"Name": "Trained model",
						"DataSourceId": null,
						"TrainedModelId": null,
						"TransformModuleId": null,
						"Language": "DotNet",
						"Version": "4.5.0",
						"PortIndex": null,
						"NodeId": "d70d4b2c-a5fa-42a5-b8dd-dd13243f0ea3-175"
					}, {
						"Name": "Dataset",
						"DataSourceId": null,
						"TrainedModelId": null,
						"TransformModuleId": null,
						"Language": "DotNet",
						"Version": "4.5.0",
						"PortIndex": null,
						"NodeId": "d70d4b2c-a5fa-42a5-b8dd-dd13243f0ea3-175"
					}
				],
				"OutputPortsInternal": [{
						"Name": "Scored dataset",
						"NodeId": "d70d4b2c-a5fa-42a5-b8dd-dd13243f0ea3-175",
						"OutputType": null
					}
				]
			}, {
				"Id": "d70d4b2c-a5fa-42a5-b8dd-dd13243f0ea3-180",
				"ModuleId": "506153734175476c4f62416c57734963.927d65ac3b504694990320f6c1672089.v1-default-1740",
				"Comment": "",
				"CommentCollapsed": true,
				"Language": "DotNet",
				"Version": "4.5.0",
				"UsePreviousResults": false,
				"ModuleParameters": [],
				"IsPartOfPartialRun": false,
				"InputPortsInternal": [{
						"Name": "Scored dataset",
						"DataSourceId": null,
						"TrainedModelId": null,
						"TransformModuleId": null,
						"Language": "DotNet",
						"Version": "4.5.0",
						"PortIndex": null,
						"NodeId": "d70d4b2c-a5fa-42a5-b8dd-dd13243f0ea3-180"
					}, {
						"Name": "Scored dataset to compare",
						"DataSourceId": null,
						"TrainedModelId": null,
						"TransformModuleId": null,
						"Language": "DotNet",
						"Version": "4.5.0",
						"PortIndex": null,
						"NodeId": "d70d4b2c-a5fa-42a5-b8dd-dd13243f0ea3-180"
					}
				],
				"OutputPortsInternal": [{
						"Name": "Evaluation results",
						"NodeId": "d70d4b2c-a5fa-42a5-b8dd-dd13243f0ea3-180",
						"OutputType": null
					}
				]
			}, {
				"Id": "d70d4b2c-a5fa-42a5-b8dd-dd13243f0ea3-10353",
				"ModuleId": "506153734175476c4f62416c57734963.5cc7053eaa30450d96c0dae4be720977.v1-default-1562",
				"Comment": "",
				"CommentCollapsed": true,
				"Language": "DotNet",
				"Version": "4.5.0",
				"UsePreviousResults": false,
				"ModuleParameters": [{
						"ValueType": "Literal",
						"LinkedGlobalParameter": null,
						"Name": "Label column",
						"Value": "%7B%22isFilter%22%3Atrue%2C%22rules%22%3A%5B%7B%22ruleType%22%3A%22ColumnNames%22%2C%22columns%22%3A%5B%22ARR_DELAY%22%5D%2C%22exclude%22%3Afalse%7D%5D%2C%22ui%22%3A%7B%22withRules%22%3Atrue%7D%7D"
					}
				],
				"IsPartOfPartialRun": false,
				"InputPortsInternal": [{
						"Name": "Untrained model",
						"DataSourceId": null,
						"TrainedModelId": null,
						"TransformModuleId": null,
						"Language": "DotNet",
						"Version": "4.5.0",
						"PortIndex": null,
						"NodeId": "d70d4b2c-a5fa-42a5-b8dd-dd13243f0ea3-10353"
					}, {
						"Name": "Dataset",
						"DataSourceId": null,
						"TrainedModelId": null,
						"TransformModuleId": null,
						"Language": "DotNet",
						"Version": "4.5.0",
						"PortIndex": null,
						"NodeId": "d70d4b2c-a5fa-42a5-b8dd-dd13243f0ea3-10353"
					}
				],
				"OutputPortsInternal": [{
						"Name": "Trained model",
						"NodeId": "d70d4b2c-a5fa-42a5-b8dd-dd13243f0ea3-10353",
						"OutputType": null
					}
				]
			}, {
				"Id": "d70d4b2c-a5fa-42a5-b8dd-dd13243f0ea3-10358",
				"ModuleId": "506153734175476c4f62416c57734963.401b4f92e7244d5abe81d5b0ff9bdb33.v1-default-1730",
				"Comment": "",
				"CommentCollapsed": true,
				"Language": "DotNet",
				"Version": "4.5.0",
				"UsePreviousResults": false,
				"ModuleParameters": [{
						"ValueType": "Literal",
						"LinkedGlobalParameter": null,
						"Name": "Append score columns to output",
						"Value": "True"
					}
				],
				"IsPartOfPartialRun": false,
				"InputPortsInternal": [{
						"Name": "Trained model",
						"DataSourceId": null,
						"TrainedModelId": null,
						"TransformModuleId": null,
						"Language": "DotNet",
						"Version": "4.5.0",
						"PortIndex": null,
						"NodeId": "d70d4b2c-a5fa-42a5-b8dd-dd13243f0ea3-10358"
					}, {
						"Name": "Dataset",
						"DataSourceId": null,
						"TrainedModelId": null,
						"TransformModuleId": null,
						"Language": "DotNet",
						"Version": "4.5.0",
						"PortIndex": null,
						"NodeId": "d70d4b2c-a5fa-42a5-b8dd-dd13243f0ea3-10358"
					}
				],
				"OutputPortsInternal": [{
						"Name": "Scored dataset",
						"NodeId": "d70d4b2c-a5fa-42a5-b8dd-dd13243f0ea3-10358",
						"OutputType": null
					}
				]
			}, {
				"Id": "dde4e237-28a6-46e3-a91f-018522b797b8-469",
				"ModuleId": "506153734175476c4f62416c57734963.b0fd7660eeed43c5948720d9cc79ed5d.v1-default-1685",
				"Comment": "",
				"CommentCollapsed": true,
				"Language": "DotNet",
				"Version": "4.5.0",
				"UsePreviousResults": false,
				"ModuleParameters": [{
						"ValueType": "Literal",
						"LinkedGlobalParameter": null,
						"Name": "Create trainer mode",
						"Value": "SingleParameter"
					}, {
						"ValueType": "Literal",
						"LinkedGlobalParameter": null,
						"Name": "Optimization tolerance",
						"Value": "1E-07"
					}, {
						"ValueType": "Literal",
						"LinkedGlobalParameter": null,
						"Name": "L1 regularization weight",
						"Value": "1"
					}, {
						"ValueType": "Literal",
						"LinkedGlobalParameter": null,
						"Name": "L2 regularization weight",
						"Value": "1"
					}, {
						"ValueType": "Literal",
						"LinkedGlobalParameter": null,
						"Name": "Memory size for L-BFGS the lower the value the faster and less accurate the training",
						"Value": "20"
					}, {
						"ValueType": "Literal",
						"LinkedGlobalParameter": null,
						"Name": "Random number seed",
						"Value": ""
					}, {
						"ValueType": "Literal",
						"LinkedGlobalParameter": null,
						"Name": "Allow unknown levels in categorical features",
						"Value": "True"
					}
				],
				"IsPartOfPartialRun": false,
				"InputPortsInternal": [],
				"OutputPortsInternal": [{
						"Name": "Untrained model",
						"NodeId": "dde4e237-28a6-46e3-a91f-018522b797b8-469",
						"OutputType": null
					}
				]
			}, {
				"Id": "ad2a383c-eb49-4196-9d0e-e46b2593192e-84275",
				"ModuleId": "506153734175476c4f62416c57734963.ebc29f52719d4d0fb66a2ce85f527c7d.v1-default-1687",
				"Comment": "",
				"CommentCollapsed": true,
				"Language": "DotNet",
				"Version": "4.5.0",
				"UsePreviousResults": false,
				"ModuleParameters": [{
						"ValueType": "Literal",
						"LinkedGlobalParameter": null,
						"Name": "Create trainer mode",
						"Value": "SingleParameter"
					}, {
						"ValueType": "Literal",
						"LinkedGlobalParameter": null,
						"Name": "Hidden layer specification",
						"Value": "Fully-connected case"
					}, {
						"ValueType": "Literal",
						"LinkedGlobalParameter": null,
						"Name": "Number of hidden nodes",
						"Value": "16"
					}, {
						"ValueType": "Literal",
						"LinkedGlobalParameter": null,
						"Name": "The learning rate",
						"Value": "0.1"
					}, {
						"ValueType": "Literal",
						"LinkedGlobalParameter": null,
						"Name": "Number of learning iterations",
						"Value": "100"
					}, {
						"ValueType": "Literal",
						"LinkedGlobalParameter": null,
						"Name": "The initial learning weights diameter",
						"Value": "0.1"
					}, {
						"ValueType": "Literal",
						"LinkedGlobalParameter": null,
						"Name": "The momentum",
						"Value": "0"
					}, {
						"ValueType": "Literal",
						"LinkedGlobalParameter": null,
						"Name": "The type of normalizer",
						"Value": "Min-Max normalizer"
					}, {
						"ValueType": "Literal",
						"LinkedGlobalParameter": null,
						"Name": "Shuffle examples",
						"Value": "True"
					}, {
						"ValueType": "Literal",
						"LinkedGlobalParameter": null,
						"Name": "Random number seed",
						"Value": ""
					}, {
						"ValueType": "Literal",
						"LinkedGlobalParameter": null,
						"Name": "Allow unknown levels in categorical features",
						"Value": "True"
					}
				],
				"IsPartOfPartialRun": false,
				"InputPortsInternal": [],
				"OutputPortsInternal": [{
						"Name": "Untrained model",
						"NodeId": "ad2a383c-eb49-4196-9d0e-e46b2593192e-84275",
						"OutputType": null
					}
				]
			}
		],
		"SerializedClientData": "<?xml version='1.0' encoding='utf-16'?><DataV1 xmlns:xsd='http://www.w3.org/2001/XMLSchema' xmlns:xsi='http://www.w3.org/2001/XMLSchema-instance'><Meta /><NodePositions><NodePosition Node='d70d4b2c-a5fa-42a5-b8dd-dd13243f0ea3-133' Position='436,494,200,200'/><NodePosition Node='abea56e0cdb841b597321e6fe9086956.1e96e0d6676f455db94755d700605ae9.v1-default-5' Position='437,276,200,200'/><NodePosition Node='d70d4b2c-a5fa-42a5-b8dd-dd13243f0ea3-170' Position='247,676,200,200'/><NodePosition Node='d70d4b2c-a5fa-42a5-b8dd-dd13243f0ea3-175' Position='430,809,200,200'/><NodePosition Node='d70d4b2c-a5fa-42a5-b8dd-dd13243f0ea3-180' Position='597,936,200,200'/><NodePosition Node='d70d4b2c-a5fa-42a5-b8dd-dd13243f0ea3-10353' Position='886,674,200,200'/><NodePosition Node='d70d4b2c-a5fa-42a5-b8dd-dd13243f0ea3-10358' Position='775,804,200,200'/><NodePosition Node='dde4e237-28a6-46e3-a91f-018522b797b8-469' Position='74,496,200,200'/><NodePosition Node='ad2a383c-eb49-4196-9d0e-e46b2593192e-84275' Position='922,494,200,200'/></NodePositions><NodeGroups /></DataV1>",
		"PublishInfo": null,
		"Parameters": null,
		"EdgesInternal": [{
				"SourceOutputPortId": "d70d4b2c-a5fa-42a5-b8dd-dd13243f0ea3-133:Results dataset1",
				"DestinationInputPortId": "d70d4b2c-a5fa-42a5-b8dd-dd13243f0ea3-170:Dataset",
				"DestinationInputPortIndex": null
			}, {
				"SourceOutputPortId": "d70d4b2c-a5fa-42a5-b8dd-dd13243f0ea3-133:Results dataset1",
				"DestinationInputPortId": "d70d4b2c-a5fa-42a5-b8dd-dd13243f0ea3-10353:Dataset",
				"DestinationInputPortIndex": null
			}, {
				"SourceOutputPortId": "d70d4b2c-a5fa-42a5-b8dd-dd13243f0ea3-133:Results dataset2",
				"DestinationInputPortId": "d70d4b2c-a5fa-42a5-b8dd-dd13243f0ea3-175:Dataset",
				"DestinationInputPortIndex": null
			}, {
				"SourceOutputPortId": "d70d4b2c-a5fa-42a5-b8dd-dd13243f0ea3-133:Results dataset2",
				"DestinationInputPortId": "d70d4b2c-a5fa-42a5-b8dd-dd13243f0ea3-10358:Dataset",
				"DestinationInputPortIndex": null
			}, {
				"SourceOutputPortId": "d70d4b2c-a5fa-42a5-b8dd-dd13243f0ea3-170:Trained model",
				"DestinationInputPortId": "d70d4b2c-a5fa-42a5-b8dd-dd13243f0ea3-175:Trained model",
				"DestinationInputPortIndex": null
			}, {
				"SourceOutputPortId": "d70d4b2c-a5fa-42a5-b8dd-dd13243f0ea3-175:Scored dataset",
				"DestinationInputPortId": "d70d4b2c-a5fa-42a5-b8dd-dd13243f0ea3-180:Scored dataset",
				"DestinationInputPortIndex": null
			}, {
				"SourceOutputPortId": "d70d4b2c-a5fa-42a5-b8dd-dd13243f0ea3-10353:Trained model",
				"DestinationInputPortId": "d70d4b2c-a5fa-42a5-b8dd-dd13243f0ea3-10358:Trained model",
				"DestinationInputPortIndex": null
			}, {
				"SourceOutputPortId": "d70d4b2c-a5fa-42a5-b8dd-dd13243f0ea3-10358:Scored dataset",
				"DestinationInputPortId": "d70d4b2c-a5fa-42a5-b8dd-dd13243f0ea3-180:Scored dataset to compare",
				"DestinationInputPortIndex": null
			}, {
				"SourceOutputPortId": "dde4e237-28a6-46e3-a91f-018522b797b8-469:Untrained model",
				"DestinationInputPortId": "d70d4b2c-a5fa-42a5-b8dd-dd13243f0ea3-170:Untrained model",
				"DestinationInputPortIndex": null
			}, {
				"SourceOutputPortId": "ad2a383c-eb49-4196-9d0e-e46b2593192e-84275:Untrained model",
				"DestinationInputPortId": "d70d4b2c-a5fa-42a5-b8dd-dd13243f0ea3-10353:Untrained model",
				"DestinationInputPortIndex": null
			}
		]
	},
	"Status": {
		"StatusCode": "InDraft",
		"StatusDetail": "None",
		"CreationTime": "\/Date(1540851436489)\/",
		"StartTime": "\/Date(-62135596800000)\/",
		"EndTime": "\/Date(-62135596800000)\/",
		"Metadata": null
	},
	"Etag": "W/\"datetime'2018-10-29T22%3A17%3A16.5053015Z'\"",
	"NodeStatuses": [{
			"NodeId": "d70d4b2c-a5fa-42a5-b8dd-dd13243f0ea3-133",
			"Status": {
				"StatusCode": "Finished",
				"StatusDetail": "Task output was present in output cache",
				"CreationTime": "\/Date(1540851251671)\/",
				"StartTime": "\/Date(1540851257947)\/",
				"EndTime": "\/Date(1540851257947)\/",
				"Metadata": {
					"Results dataset1": [{
							"Name": "visualization",
							"Value": "experimentoutput/6fb420ca-99ad-4d7c-a583-9439e49beb6c/8c7ea317-5539-4f10-9f5c-2b9d8b24de48"
						}, {
							"Name": "schema",
							"Value": "experimentoutput/6fb420ca-99ad-4d7c-a583-9439e49beb6c/7463b2f3-976a-4038-91c3-6686d03d02dd"
						}
					],
					"Results dataset2": [{
							"Name": "visualization",
							"Value": "experimentoutput/1dd18b02-9447-4801-b98a-337f2cc437ef/eda5be20-1fde-45bf-8829-5b6fccd09547"
						}, {
							"Name": "schema",
							"Value": "experimentoutput/1dd18b02-9447-4801-b98a-337f2cc437ef/00ad7f57-2c1e-4000-a69e-98d3003640ce"
						}
					]
				}
			},
			"StandardErrorEndpoint": null,
			"StandardOutEndpoint": null,
			"OutputEndpoints": [{
					"BaseUri": "https://studio.azureml.net/",
					"Size": 7789287,
					"Name": "Results dataset1",
					"EndpointType": "SasEndpoint",
					"CredentialContainer": "Inline",
					"AccessCredential": "?workspaceId=abea56e0cdb841b597321e6fe9086956&signature=Rhi45BhbLFsi6ouxBpB69hMsH7SIQL732xvDgDBVr8U%3D&sharedAccessUri=https%3A%2F%2Fesprodussouthsus.blob.core.windows.net%2Fexperimentoutput%2F6fb420ca-99ad-4d7c-a583-9439e49beb6c%2F6fb420ca-99ad-4d7c-a583-9439e49beb6c.dataset%3Fsv%3D2015-02-21%26sr%3Db%26sig%3DoXVUvGOF6o8rF6AV0GFnM9SsCW9Au2QeeO0bZjoFfkk%3D%26st%3D2018-10-29T22%3A13%3A52Z%26se%3D2018-10-30T22%3A18%3A52Z%26sp%3Dr",
					"Location": "api/sharedaccess",
					"FileType": "File",
					"IsAuxiliary": false
				}, {
					"BaseUri": "https://studio.azureml.net/",
					"Size": 2599412,
					"Name": "Results dataset2",
					"EndpointType": "SasEndpoint",
					"CredentialContainer": "Inline",
					"AccessCredential": "?workspaceId=abea56e0cdb841b597321e6fe9086956&signature=tWZ%2BXvklRMm4Mz%2FqfUNSQ2kwtkDablBLJwOjcNuWDzY%3D&sharedAccessUri=https%3A%2F%2Fesprodussouthsus.blob.core.windows.net%2Fexperimentoutput%2F1dd18b02-9447-4801-b98a-337f2cc437ef%2F1dd18b02-9447-4801-b98a-337f2cc437ef.dataset%3Fsv%3D2015-02-21%26sr%3Db%26sig%3DTL%2BVegOeKGtokq9OmrlhrUM99iqwEdlWzk9D74EoOoY%3D%26st%3D2018-10-29T22%3A13%3A52Z%26se%3D2018-10-30T22%3A18%3A52Z%26sp%3Dr",
					"Location": "api/sharedaccess",
					"FileType": "File",
					"IsAuxiliary": false
				}
			],
			"MetadataOutputEndpoints": {
				"Results dataset1": [{
						"Key": "visualization",
						"Value": {
							"BaseUri": "https://studio.azureml.net/",
							"Size": -1,
							"Name": "Results dataset1",
							"EndpointType": "SasEndpoint",
							"CredentialContainer": "Inline",
							"AccessCredential": "?workspaceId=abea56e0cdb841b597321e6fe9086956&signature=E2cZ%2FWPayon9%2F3fuSICj2eZaEuV7Bmb1ROHPMDMFxMw%3D&sharedAccessUri=https%3A%2F%2Fesprodussouthsus.blob.core.windows.net%2Fexperimentoutput%2F6fb420ca-99ad-4d7c-a583-9439e49beb6c%2F8c7ea317-5539-4f10-9f5c-2b9d8b24de48%3Fsv%3D2015-02-21%26sr%3Db%26sig%3DjGt9PNxlTiAVYxEDdHCvzS%2FXlo59%2BvvBrEjNzQkFEC0%3D%26st%3D2018-10-29T22%3A13%3A52Z%26se%3D2018-10-30T22%3A18%3A52Z%26sp%3Dr",
							"Location": "api/sharedaccess",
							"FileType": "File",
							"IsAuxiliary": false
						}
					}, {
						"Key": "schema",
						"Value": {
							"BaseUri": "https://studio.azureml.net/",
							"Size": -1,
							"Name": "Results dataset1",
							"EndpointType": "SasEndpoint",
							"CredentialContainer": "Inline",
							"AccessCredential": "?workspaceId=abea56e0cdb841b597321e6fe9086956&signature=FB8QY13gOGtNknR3pDJfcE8tXcTZ2eQBqk4im1MDQeE%3D&sharedAccessUri=https%3A%2F%2Fesprodussouthsus.blob.core.windows.net%2Fexperimentoutput%2F6fb420ca-99ad-4d7c-a583-9439e49beb6c%2F7463b2f3-976a-4038-91c3-6686d03d02dd%3Fsv%3D2015-02-21%26sr%3Db%26sig%3DqhjmTnu4UtBDtEWfwnZxd91i5Ai5h%2B0Ehjd%2Fo8BgSdU%3D%26st%3D2018-10-29T22%3A13%3A52Z%26se%3D2018-10-30T22%3A18%3A52Z%26sp%3Dr",
							"Location": "api/sharedaccess",
							"FileType": "File",
							"IsAuxiliary": false
						}
					}
				],
				"Results dataset2": [{
						"Key": "visualization",
						"Value": {
							"BaseUri": "https://studio.azureml.net/",
							"Size": -1,
							"Name": "Results dataset2",
							"EndpointType": "SasEndpoint",
							"CredentialContainer": "Inline",
							"AccessCredential": "?workspaceId=abea56e0cdb841b597321e6fe9086956&signature=%2BgxejmOUTtaBWHCPOwvG%2F1BiKTiYQByeZOLcmnJrcXo%3D&sharedAccessUri=https%3A%2F%2Fesprodussouthsus.blob.core.windows.net%2Fexperimentoutput%2F1dd18b02-9447-4801-b98a-337f2cc437ef%2Feda5be20-1fde-45bf-8829-5b6fccd09547%3Fsv%3D2015-02-21%26sr%3Db%26sig%3DoJT%2F6pA19nQ5f1k7TB7NkSqinWvSXG7l3ByQQf5afgA%3D%26st%3D2018-10-29T22%3A13%3A52Z%26se%3D2018-10-30T22%3A18%3A52Z%26sp%3Dr",
							"Location": "api/sharedaccess",
							"FileType": "File",
							"IsAuxiliary": false
						}
					}, {
						"Key": "schema",
						"Value": {
							"BaseUri": "https://studio.azureml.net/",
							"Size": -1,
							"Name": "Results dataset2",
							"EndpointType": "SasEndpoint",
							"CredentialContainer": "Inline",
							"AccessCredential": "?workspaceId=abea56e0cdb841b597321e6fe9086956&signature=ydhuqXB4vDPoTpD57YrezL4G7SUUqhO58Cqu4BYPVp8%3D&sharedAccessUri=https%3A%2F%2Fesprodussouthsus.blob.core.windows.net%2Fexperimentoutput%2F1dd18b02-9447-4801-b98a-337f2cc437ef%2F00ad7f57-2c1e-4000-a69e-98d3003640ce%3Fsv%3D2015-02-21%26sr%3Db%26sig%3DM2yQUS6ITGISgRz18MyFjlRSgT93idmUQLqaHs7KTF0%3D%26st%3D2018-10-29T22%3A13%3A52Z%26se%3D2018-10-30T22%3A18%3A52Z%26sp%3Dr",
							"Location": "api/sharedaccess",
							"FileType": "File",
							"IsAuxiliary": false
						}
					}
				]
			}
		}, {
			"NodeId": "dde4e237-28a6-46e3-a91f-018522b797b8-469",
			"Status": {
				"StatusCode": "Finished",
				"StatusDetail": "Task output was present in output cache",
				"CreationTime": "\/Date(1540851251703)\/",
				"StartTime": "\/Date(1540851258463)\/",
				"EndTime": "\/Date(1540851258463)\/",
				"Metadata": {
					"Untrained model": [{
							"Name": "visualization",
							"Value": "experimentoutput/8289a0f2-7186-4476-a5e1-8964c6321aeb/ace52be5-8b5d-4e4d-9f09-28971c7009cc"
						}, {
							"Name": "runtimeinfo",
							"Value": "experimentoutput/8289a0f2-7186-4476-a5e1-8964c6321aeb/a4c7da64-02e1-4b80-ad0e-3589aa6e63f6"
						}
					]
				}
			},
			"StandardErrorEndpoint": null,
			"StandardOutEndpoint": null,
			"OutputEndpoints": [{
					"BaseUri": "https://studio.azureml.net/",
					"Size": 4667,
					"Name": "Untrained model",
					"EndpointType": "SasEndpoint",
					"CredentialContainer": "Inline",
					"AccessCredential": "?workspaceId=abea56e0cdb841b597321e6fe9086956&signature=onPli158smVCPuGbVby3jHHOSdZ6WoENG7cNz4Ghofw%3D&sharedAccessUri=https%3A%2F%2Fesprodussouthsus.blob.core.windows.net%2Fexperimentoutput%2F8289a0f2-7186-4476-a5e1-8964c6321aeb%2F8289a0f2-7186-4476-a5e1-8964c6321aeb.ilearner%3Fsv%3D2015-02-21%26sr%3Db%26sig%3D9tOh9m9KsY5qurnfLchXyQn2sMxL2c0FOh0S%2F%2F212LY%3D%26st%3D2018-10-29T22%3A13%3A52Z%26se%3D2018-10-30T22%3A18%3A52Z%26sp%3Dr",
					"Location": "api/sharedaccess",
					"FileType": "File",
					"IsAuxiliary": false
				}
			],
			"MetadataOutputEndpoints": {
				"Untrained model": [{
						"Key": "visualization",
						"Value": {
							"BaseUri": "https://studio.azureml.net/",
							"Size": -1,
							"Name": "Untrained model",
							"EndpointType": "SasEndpoint",
							"CredentialContainer": "Inline",
							"AccessCredential": "?workspaceId=abea56e0cdb841b597321e6fe9086956&signature=uyTWLUvQoulOd%2BtVnWcyK7TkWW%2FZbmNFGgAZ3ngPUUc%3D&sharedAccessUri=https%3A%2F%2Fesprodussouthsus.blob.core.windows.net%2Fexperimentoutput%2F8289a0f2-7186-4476-a5e1-8964c6321aeb%2Face52be5-8b5d-4e4d-9f09-28971c7009cc%3Fsv%3D2015-02-21%26sr%3Db%26sig%3DFA21eSUvSjjMrJw1YDzcTuYIg8cvrrQCmaqtUGQUdXw%3D%26st%3D2018-10-29T22%3A13%3A52Z%26se%3D2018-10-30T22%3A18%3A52Z%26sp%3Dr",
							"Location": "api/sharedaccess",
							"FileType": "File",
							"IsAuxiliary": false
						}
					}, {
						"Key": "runtimeinfo",
						"Value": {
							"BaseUri": "https://studio.azureml.net/",
							"Size": -1,
							"Name": "Untrained model",
							"EndpointType": "SasEndpoint",
							"CredentialContainer": "Inline",
							"AccessCredential": "?workspaceId=abea56e0cdb841b597321e6fe9086956&signature=JVkPK7Y05cXSlYgtGI19PcaRteQpEUpGsfHU0OLiRnw%3D&sharedAccessUri=https%3A%2F%2Fesprodussouthsus.blob.core.windows.net%2Fexperimentoutput%2F8289a0f2-7186-4476-a5e1-8964c6321aeb%2Fa4c7da64-02e1-4b80-ad0e-3589aa6e63f6%3Fsv%3D2015-02-21%26sr%3Db%26sig%3DaPEbSqjwKlJjkwyT5DWpre679KPOz%2BzLMw9xuakX2%2F4%3D%26st%3D2018-10-29T22%3A13%3A52Z%26se%3D2018-10-30T22%3A18%3A52Z%26sp%3Dr",
							"Location": "api/sharedaccess",
							"FileType": "File",
							"IsAuxiliary": false
						}
					}
				]
			}
		}, {
			"NodeId": "ad2a383c-eb49-4196-9d0e-e46b2593192e-84275",
			"Status": {
				"StatusCode": "Finished",
				"StatusDetail": "None",
				"CreationTime": "\/Date(1540851251750)\/",
				"StartTime": "\/Date(1540851258931)\/",
				"EndTime": "\/Date(1540851261760)\/",
				"Metadata": {
					"Untrained model": [{
							"Name": "visualization",
							"Value": "experimentoutput/52f69330-3f8f-4f90-99a3-aaf7420b9488/461b6d27-3bd5-47d0-88eb-d856c0663501"
						}, {
							"Name": "runtimeinfo",
							"Value": "experimentoutput/52f69330-3f8f-4f90-99a3-aaf7420b9488/fd95bbd2-af54-4d96-b25a-8dfffe3ed8fc"
						}
					]
				}
			},
			"StandardErrorEndpoint": {
				"BaseUri": "https://studio.azureml.net/",
				"Size": 90,
				"Name": "defaultSasName",
				"EndpointType": "SasEndpoint",
				"CredentialContainer": "Inline",
				"AccessCredential": "?workspaceId=abea56e0cdb841b597321e6fe9086956&signature=ohoxEVOBRQbM%2FRWWYjhLPGEZZVtMTHfskPmqAJN8gh8%3D&sharedAccessUri=https%3A%2F%2Fesprodussouth001.blob.core.windows.net%2Fexperimentoutput%2F99737161-c141-4551-8f27-fba9b17a900e%2F99737161-c141-4551-8f27-fba9b17a900e.txt%3Fsv%3D2015-02-21%26sr%3Db%26sig%3D%2FW1%2BwIjoAFVv0J%2FuQFFEhO4cLAH5qW7fMKeG07B14io%3D%26st%3D2018-10-29T22%3A13%3A52Z%26se%3D2018-10-30T22%3A18%3A52Z%26sp%3Dr",
				"Location": "api/sharedaccess",
				"FileType": "File",
				"IsAuxiliary": false
			},
			"StandardOutEndpoint": {
				"BaseUri": "https://studio.azureml.net/",
				"Size": 9825,
				"Name": "defaultSasName",
				"EndpointType": "SasEndpoint",
				"CredentialContainer": "Inline",
				"AccessCredential": "?workspaceId=abea56e0cdb841b597321e6fe9086956&signature=TR%2BKacVkl8lI8VZutiCN51NxuD2SH61%2BT41W8qwtnCM%3D&sharedAccessUri=https%3A%2F%2Fesprodussouth001.blob.core.windows.net%2Fexperimentoutput%2F95f5408f-5e74-4b02-b398-59f0cad0abc6%2F95f5408f-5e74-4b02-b398-59f0cad0abc6.txt%3Fsv%3D2015-02-21%26sr%3Db%26sig%3Ddh5vjfWqqtFwELUNJPy1daKVo2XrjH13mCt2O0hziV8%3D%26st%3D2018-10-29T22%3A13%3A52Z%26se%3D2018-10-30T22%3A18%3A52Z%26sp%3Dr",
				"Location": "api/sharedaccess",
				"FileType": "File",
				"IsAuxiliary": false
			},
			"OutputEndpoints": [{
					"BaseUri": "https://studio.azureml.net/",
					"Size": 5816,
					"Name": "Untrained model",
					"EndpointType": "SasEndpoint",
					"CredentialContainer": "Inline",
					"AccessCredential": "?workspaceId=abea56e0cdb841b597321e6fe9086956&signature=XXxjh5tPczeLJuR3Mn41ejmqg87rC4UMss1T5R65qto%3D&sharedAccessUri=https%3A%2F%2Fesprodussouthsus.blob.core.windows.net%2Fexperimentoutput%2F52f69330-3f8f-4f90-99a3-aaf7420b9488%2F52f69330-3f8f-4f90-99a3-aaf7420b9488.ilearner%3Fsv%3D2015-02-21%26sr%3Db%26sig%3Di%2F3WBp6YgxugbGF9f3gXnIYXsK6fCxBY4AjVYv1MuJE%3D%26st%3D2018-10-29T22%3A13%3A52Z%26se%3D2018-10-30T22%3A18%3A52Z%26sp%3Dr",
					"Location": "api/sharedaccess",
					"FileType": "File",
					"IsAuxiliary": false
				}
			],
			"MetadataOutputEndpoints": {
				"Untrained model": [{
						"Key": "visualization",
						"Value": {
							"BaseUri": "https://studio.azureml.net/",
							"Size": -1,
							"Name": "Untrained model",
							"EndpointType": "SasEndpoint",
							"CredentialContainer": "Inline",
							"AccessCredential": "?workspaceId=abea56e0cdb841b597321e6fe9086956&signature=XDSPVKZJCXcbWFK35XTkJx1YuQyqtBGJg5CBwa%2F1Vg4%3D&sharedAccessUri=https%3A%2F%2Fesprodussouthsus.blob.core.windows.net%2Fexperimentoutput%2F52f69330-3f8f-4f90-99a3-aaf7420b9488%2F461b6d27-3bd5-47d0-88eb-d856c0663501%3Fsv%3D2015-02-21%26sr%3Db%26sig%3DXGLu0RtH9uOPca2tca1nr3DUqJDB9VOIykARdvjXvAQ%3D%26st%3D2018-10-29T22%3A13%3A52Z%26se%3D2018-10-30T22%3A18%3A52Z%26sp%3Dr",
							"Location": "api/sharedaccess",
							"FileType": "File",
							"IsAuxiliary": false
						}
					}, {
						"Key": "runtimeinfo",
						"Value": {
							"BaseUri": "https://studio.azureml.net/",
							"Size": -1,
							"Name": "Untrained model",
							"EndpointType": "SasEndpoint",
							"CredentialContainer": "Inline",
							"AccessCredential": "?workspaceId=abea56e0cdb841b597321e6fe9086956&signature=Sas94uMDG7FvBDZJthQAXsSCfHjZZo8Ies7ZURZBu0A%3D&sharedAccessUri=https%3A%2F%2Fesprodussouthsus.blob.core.windows.net%2Fexperimentoutput%2F52f69330-3f8f-4f90-99a3-aaf7420b9488%2Ffd95bbd2-af54-4d96-b25a-8dfffe3ed8fc%3Fsv%3D2015-02-21%26sr%3Db%26sig%3DaYQZmbPUJyxcP74I08h5KdHL1dy0XhrLjtpjn50PZC8%3D%26st%3D2018-10-29T22%3A13%3A52Z%26se%3D2018-10-30T22%3A18%3A52Z%26sp%3Dr",
							"Location": "api/sharedaccess",
							"FileType": "File",
							"IsAuxiliary": false
						}
					}
				]
			}
		}, {
			"NodeId": "d70d4b2c-a5fa-42a5-b8dd-dd13243f0ea3-170",
			"Status": {
				"StatusCode": "Finished",
				"StatusDetail": "Task output was present in output cache",
				"CreationTime": "\/Date(1540851251781)\/",
				"StartTime": "\/Date(1540851260947)\/",
				"EndTime": "\/Date(1540851260947)\/",
				"Metadata": {
					"Trained model": [{
							"Name": "visualization",
							"Value": "experimentoutput/c3d8831a-0373-4a63-821b-16c8d9663fb2/ece6b3d7-902b-40d3-95da-ef78dd2060e4"
						}, {
							"Name": "runtimeinfo",
							"Value": "experimentoutput/c3d8831a-0373-4a63-821b-16c8d9663fb2/c027104b-4651-4489-ae99-1876a7796407"
						}
					]
				}
			},
			"StandardErrorEndpoint": null,
			"StandardOutEndpoint": null,
			"OutputEndpoints": [{
					"BaseUri": "https://studio.azureml.net/",
					"Size": 36818,
					"Name": "Trained model",
					"EndpointType": "SasEndpoint",
					"CredentialContainer": "Inline",
					"AccessCredential": "?workspaceId=abea56e0cdb841b597321e6fe9086956&signature=JvfGKxBOC4AWf2VvRmmE7TbuoQFkCa4g9rxnOh8e8vM%3D&sharedAccessUri=https%3A%2F%2Fesprodussouthsus.blob.core.windows.net%2Fexperimentoutput%2Fc3d8831a-0373-4a63-821b-16c8d9663fb2%2Fc3d8831a-0373-4a63-821b-16c8d9663fb2.ilearner%3Fsv%3D2015-02-21%26sr%3Db%26sig%3DxSbcUfis7K%2FtvZwcSiDujc6JGOHsPCBHPSAnIKcZJ64%3D%26st%3D2018-10-29T22%3A13%3A52Z%26se%3D2018-10-30T22%3A18%3A52Z%26sp%3Dr",
					"Location": "api/sharedaccess",
					"FileType": "File",
					"IsAuxiliary": false
				}
			],
			"MetadataOutputEndpoints": {
				"Trained model": [{
						"Key": "visualization",
						"Value": {
							"BaseUri": "https://studio.azureml.net/",
							"Size": -1,
							"Name": "Trained model",
							"EndpointType": "SasEndpoint",
							"CredentialContainer": "Inline",
							"AccessCredential": "?workspaceId=abea56e0cdb841b597321e6fe9086956&signature=UBs%2FcGNTHJ5IJbcQ5CE7hmTpth2WIUzAdQNjsLMSqHs%3D&sharedAccessUri=https%3A%2F%2Fesprodussouthsus.blob.core.windows.net%2Fexperimentoutput%2Fc3d8831a-0373-4a63-821b-16c8d9663fb2%2Fece6b3d7-902b-40d3-95da-ef78dd2060e4%3Fsv%3D2015-02-21%26sr%3Db%26sig%3DB8h22q5MeFsZT8gFHkQepqh%2BBBJkMIDQf5xNuTccOJE%3D%26st%3D2018-10-29T22%3A13%3A52Z%26se%3D2018-10-30T22%3A18%3A52Z%26sp%3Dr",
							"Location": "api/sharedaccess",
							"FileType": "File",
							"IsAuxiliary": false
						}
					}, {
						"Key": "runtimeinfo",
						"Value": {
							"BaseUri": "https://studio.azureml.net/",
							"Size": -1,
							"Name": "Trained model",
							"EndpointType": "SasEndpoint",
							"CredentialContainer": "Inline",
							"AccessCredential": "?workspaceId=abea56e0cdb841b597321e6fe9086956&signature=BmLlU33uB8cWHIe8GdtkTo%2B2yxYywBMNKerh4KStwc0%3D&sharedAccessUri=https%3A%2F%2Fesprodussouthsus.blob.core.windows.net%2Fexperimentoutput%2Fc3d8831a-0373-4a63-821b-16c8d9663fb2%2Fc027104b-4651-4489-ae99-1876a7796407%3Fsv%3D2015-02-21%26sr%3Db%26sig%3De9e9iaZwWpqcwGq8T7ERjYX4zVvb%2BHheGRgit3crhvg%3D%26st%3D2018-10-29T22%3A13%3A52Z%26se%3D2018-10-30T22%3A18%3A52Z%26sp%3Dr",
							"Location": "api/sharedaccess",
							"FileType": "File",
							"IsAuxiliary": false
						}
					}
				]
			}
		}, {
			"NodeId": "d70d4b2c-a5fa-42a5-b8dd-dd13243f0ea3-10353",
			"Status": {
				"StatusCode": "Finished",
				"StatusDetail": "None",
				"CreationTime": "\/Date(1540851251796)\/",
				"StartTime": "\/Date(1540851265089)\/",
				"EndTime": "\/Date(1540851312607)\/",
				"Metadata": {
					"Trained model": [{
							"Name": "visualization",
							"Value": "experimentoutput/c34c34e1-bbbc-4783-9723-b2ae1482fbae/6965472b-5767-41a6-93c0-99c4c6ce3d55"
						}, {
							"Name": "runtimeinfo",
							"Value": "experimentoutput/c34c34e1-bbbc-4783-9723-b2ae1482fbae/08cdf16e-8d2f-4c84-b080-111caee646be"
						}
					]
				}
			},
			"StandardErrorEndpoint": {
				"BaseUri": "https://studio.azureml.net/",
				"Size": 188,
				"Name": "defaultSasName",
				"EndpointType": "SasEndpoint",
				"CredentialContainer": "Inline",
				"AccessCredential": "?workspaceId=abea56e0cdb841b597321e6fe9086956&signature=OT7fTF414rIE1HgwaK%2B8SIqs391mfErlJ%2F%2Bg5UQUcT4%3D&sharedAccessUri=https%3A%2F%2Fesprodussouth001.blob.core.windows.net%2Fexperimentoutput%2F1bf6eab7-9acf-458b-97dc-ed5afa3abfb8%2F1bf6eab7-9acf-458b-97dc-ed5afa3abfb8.txt%3Fsv%3D2015-02-21%26sr%3Db%26sig%3DBgUQoV0RVatkxcSxNnwyqv8zHfSMVWEALf7Q3bdQqwc%3D%26st%3D2018-10-29T22%3A13%3A52Z%26se%3D2018-10-30T22%3A18%3A52Z%26sp%3Dr",
				"Location": "api/sharedaccess",
				"FileType": "File",
				"IsAuxiliary": false
			},
			"StandardOutEndpoint": {
				"BaseUri": "https://studio.azureml.net/",
				"Size": 11152,
				"Name": "defaultSasName",
				"EndpointType": "SasEndpoint",
				"CredentialContainer": "Inline",
				"AccessCredential": "?workspaceId=abea56e0cdb841b597321e6fe9086956&signature=6ZX2ulDmjLLjwZQ0TaEdOzdRNVLhLdo8muSAreEhNeM%3D&sharedAccessUri=https%3A%2F%2Fesprodussouth001.blob.core.windows.net%2Fexperimentoutput%2F0526e094-0322-4088-bc10-7b3b8bc7b478%2F0526e094-0322-4088-bc10-7b3b8bc7b478.txt%3Fsv%3D2015-02-21%26sr%3Db%26sig%3D2WJ2USZsbEq%2Fo9olUgdcsh3UymS%2B0xy1Yl6mbe8GnxI%3D%26st%3D2018-10-29T22%3A13%3A52Z%26se%3D2018-10-30T22%3A18%3A52Z%26sp%3Dr",
				"Location": "api/sharedaccess",
				"FileType": "File",
				"IsAuxiliary": false
			},
			"OutputEndpoints": [{
					"BaseUri": "https://studio.azureml.net/",
					"Size": 78678,
					"Name": "Trained model",
					"EndpointType": "SasEndpoint",
					"CredentialContainer": "Inline",
					"AccessCredential": "?workspaceId=abea56e0cdb841b597321e6fe9086956&signature=IO%2BFxI7c9i016STupLwl043n%2BhayItaUqRz0crE%2Bmsg%3D&sharedAccessUri=https%3A%2F%2Fesprodussouthsus.blob.core.windows.net%2Fexperimentoutput%2Fc34c34e1-bbbc-4783-9723-b2ae1482fbae%2Fc34c34e1-bbbc-4783-9723-b2ae1482fbae.ilearner%3Fsv%3D2015-02-21%26sr%3Db%26sig%3DJbk1KILpup%2B81FS4%2FUtjlTu0qFXlEbJms61ndFGmG7U%3D%26st%3D2018-10-29T22%3A13%3A52Z%26se%3D2018-10-30T22%3A18%3A52Z%26sp%3Dr",
					"Location": "api/sharedaccess",
					"FileType": "File",
					"IsAuxiliary": false
				}
			],
			"MetadataOutputEndpoints": {
				"Trained model": [{
						"Key": "visualization",
						"Value": {
							"BaseUri": "https://studio.azureml.net/",
							"Size": -1,
							"Name": "Trained model",
							"EndpointType": "SasEndpoint",
							"CredentialContainer": "Inline",
							"AccessCredential": "?workspaceId=abea56e0cdb841b597321e6fe9086956&signature=d0xKnKQ9XvKbTaueFEXRcgEEsYxgPxplSBtWC6zXrPM%3D&sharedAccessUri=https%3A%2F%2Fesprodussouthsus.blob.core.windows.net%2Fexperimentoutput%2Fc34c34e1-bbbc-4783-9723-b2ae1482fbae%2F6965472b-5767-41a6-93c0-99c4c6ce3d55%3Fsv%3D2015-02-21%26sr%3Db%26sig%3D23%2B2OSCrMZxuvWvCq%2BWN5DH1mJTXy11%2BdVmB6LFLM58%3D%26st%3D2018-10-29T22%3A13%3A52Z%26se%3D2018-10-30T22%3A18%3A52Z%26sp%3Dr",
							"Location": "api/sharedaccess",
							"FileType": "File",
							"IsAuxiliary": false
						}
					}, {
						"Key": "runtimeinfo",
						"Value": {
							"BaseUri": "https://studio.azureml.net/",
							"Size": -1,
							"Name": "Trained model",
							"EndpointType": "SasEndpoint",
							"CredentialContainer": "Inline",
							"AccessCredential": "?workspaceId=abea56e0cdb841b597321e6fe9086956&signature=uk7U807ckGLvhhjlXUbJ32aEw%2FakeNDJHTXZ1%2BYKC7s%3D&sharedAccessUri=https%3A%2F%2Fesprodussouthsus.blob.core.windows.net%2Fexperimentoutput%2Fc34c34e1-bbbc-4783-9723-b2ae1482fbae%2F08cdf16e-8d2f-4c84-b080-111caee646be%3Fsv%3D2015-02-21%26sr%3Db%26sig%3DaGIdZ87P0dC5ykYxWN2v2JXpfX3wptlD3ofdDZ5bc5Q%3D%26st%3D2018-10-29T22%3A13%3A52Z%26se%3D2018-10-30T22%3A18%3A52Z%26sp%3Dr",
							"Location": "api/sharedaccess",
							"FileType": "File",
							"IsAuxiliary": false
						}
					}
				]
			}
		}, {
			"NodeId": "d70d4b2c-a5fa-42a5-b8dd-dd13243f0ea3-175",
			"Status": {
				"StatusCode": "Finished",
				"StatusDetail": "Task output was present in output cache",
				"CreationTime": "\/Date(1540851251828)\/",
				"StartTime": "\/Date(1540851263141)\/",
				"EndTime": "\/Date(1540851263141)\/",
				"Metadata": {
					"Scored dataset": [{
							"Name": "visualization",
							"Value": "experimentoutput/0b4fb102-3b92-4d14-b996-87519bd343a2/2fd41504-e6e0-4f42-950a-d8fd51432bc3"
						}, {
							"Name": "schema",
							"Value": "experimentoutput/0b4fb102-3b92-4d14-b996-87519bd343a2/f1203005-4157-4ff2-abd5-e07b8b2cdcb4"
						}
					]
				}
			},
			"StandardErrorEndpoint": null,
			"StandardOutEndpoint": null,
			"OutputEndpoints": [{
					"BaseUri": "https://studio.azureml.net/",
					"Size": 2613779,
					"Name": "Scored dataset",
					"EndpointType": "SasEndpoint",
					"CredentialContainer": "Inline",
					"AccessCredential": "?workspaceId=abea56e0cdb841b597321e6fe9086956&signature=H0ldbkCsWqUnrRa5p0YCDOo%2FI%2FqeFKzR14hWWjdGrCs%3D&sharedAccessUri=https%3A%2F%2Fesprodussouthsus.blob.core.windows.net%2Fexperimentoutput%2F0b4fb102-3b92-4d14-b996-87519bd343a2%2F0b4fb102-3b92-4d14-b996-87519bd343a2.dataset%3Fsv%3D2015-02-21%26sr%3Db%26sig%3DU9jr%2BNnVUcsRBBr%2BlVv6lb8DCnsgdUX3RtCnRK7og2M%3D%26st%3D2018-10-29T22%3A13%3A52Z%26se%3D2018-10-30T22%3A18%3A52Z%26sp%3Dr",
					"Location": "api/sharedaccess",
					"FileType": "File",
					"IsAuxiliary": false
				}
			],
			"MetadataOutputEndpoints": {
				"Scored dataset": [{
						"Key": "visualization",
						"Value": {
							"BaseUri": "https://studio.azureml.net/",
							"Size": -1,
							"Name": "Scored dataset",
							"EndpointType": "SasEndpoint",
							"CredentialContainer": "Inline",
							"AccessCredential": "?workspaceId=abea56e0cdb841b597321e6fe9086956&signature=PFPCvlvAh6%2B0ksx3GYm62crTc%2BTb5iOuBzy2P%2B%2Fi6k4%3D&sharedAccessUri=https%3A%2F%2Fesprodussouthsus.blob.core.windows.net%2Fexperimentoutput%2F0b4fb102-3b92-4d14-b996-87519bd343a2%2F2fd41504-e6e0-4f42-950a-d8fd51432bc3%3Fsv%3D2015-02-21%26sr%3Db%26sig%3DsIHoqFbozUJn1ICws0I%2BC5GEdxSYD56sdJvmPNK50z0%3D%26st%3D2018-10-29T22%3A13%3A52Z%26se%3D2018-10-30T22%3A18%3A52Z%26sp%3Dr",
							"Location": "api/sharedaccess",
							"FileType": "File",
							"IsAuxiliary": false
						}
					}, {
						"Key": "schema",
						"Value": {
							"BaseUri": "https://studio.azureml.net/",
							"Size": -1,
							"Name": "Scored dataset",
							"EndpointType": "SasEndpoint",
							"CredentialContainer": "Inline",
							"AccessCredential": "?workspaceId=abea56e0cdb841b597321e6fe9086956&signature=etDB1NA%2F9kOoIwvUBBPhyTp3N0cgpn5XUlTPAsganL0%3D&sharedAccessUri=https%3A%2F%2Fesprodussouthsus.blob.core.windows.net%2Fexperimentoutput%2F0b4fb102-3b92-4d14-b996-87519bd343a2%2Ff1203005-4157-4ff2-abd5-e07b8b2cdcb4%3Fsv%3D2015-02-21%26sr%3Db%26sig%3D0NFKie74YHWnwTZ12GkCVbjiZHmRlb%2FYWkdG65HEt40%3D%26st%3D2018-10-29T22%3A13%3A52Z%26se%3D2018-10-30T22%3A18%3A52Z%26sp%3Dr",
							"Location": "api/sharedaccess",
							"FileType": "File",
							"IsAuxiliary": false
						}
					}
				]
			}
		}, {
			"NodeId": "d70d4b2c-a5fa-42a5-b8dd-dd13243f0ea3-10358",
			"Status": {
				"StatusCode": "Finished",
				"StatusDetail": "None",
				"CreationTime": "\/Date(1540851251843)\/",
				"StartTime": "\/Date(1540851316451)\/",
				"EndTime": "\/Date(1540851321206)\/",
				"Metadata": {
					"Scored dataset": [{
							"Name": "visualization",
							"Value": "experimentoutput/7a46ba19-9695-40d9-89b6-5f84f9a7f4b0/bf804378-64c9-4b2a-ad2d-2745cbcaf088"
						}, {
							"Name": "schema",
							"Value": "experimentoutput/7a46ba19-9695-40d9-89b6-5f84f9a7f4b0/09555500-6900-496d-bfb3-f2b14747c9e6"
						}
					]
				}
			},
			"StandardErrorEndpoint": {
				"BaseUri": "https://studio.azureml.net/",
				"Size": 90,
				"Name": "defaultSasName",
				"EndpointType": "SasEndpoint",
				"CredentialContainer": "Inline",
				"AccessCredential": "?workspaceId=abea56e0cdb841b597321e6fe9086956&signature=SpYZB3BiDnFe%2BGh0dvTVG8%2FtyOy7GQ2bqB8NiMTm9h8%3D&sharedAccessUri=https%3A%2F%2Fesprodussouth001.blob.core.windows.net%2Fexperimentoutput%2F0203555e-e8ec-496e-8679-93924ad17881%2F0203555e-e8ec-496e-8679-93924ad17881.txt%3Fsv%3D2015-02-21%26sr%3Db%26sig%3DXALxPCAdAu0bIqMe0S4Ja2gFnWnsyhWBbTeJy0Qo64k%3D%26st%3D2018-10-29T22%3A13%3A52Z%26se%3D2018-10-30T22%3A18%3A52Z%26sp%3Dr",
				"Location": "api/sharedaccess",
				"FileType": "File",
				"IsAuxiliary": false
			},
			"StandardOutEndpoint": {
				"BaseUri": "https://studio.azureml.net/",
				"Size": 7462,
				"Name": "defaultSasName",
				"EndpointType": "SasEndpoint",
				"CredentialContainer": "Inline",
				"AccessCredential": "?workspaceId=abea56e0cdb841b597321e6fe9086956&signature=67Urv9cycx%2FGN8ddbjnkJEIwZGL%2FBh%2FW6r6whLRine0%3D&sharedAccessUri=https%3A%2F%2Fesprodussouth001.blob.core.windows.net%2Fexperimentoutput%2F1088e54a-955c-48d3-8261-3dbbf3e96906%2F1088e54a-955c-48d3-8261-3dbbf3e96906.txt%3Fsv%3D2015-02-21%26sr%3Db%26sig%3Dut0v39cItV2qlYWFOtnhkQJpcwL4ZgzQzwEtxzSxs3k%3D%26st%3D2018-10-29T22%3A13%3A52Z%26se%3D2018-10-30T22%3A18%3A52Z%26sp%3Dr",
				"Location": "api/sharedaccess",
				"FileType": "File",
				"IsAuxiliary": false
			},
			"OutputEndpoints": [{
					"BaseUri": "https://studio.azureml.net/",
					"Size": 2871744,
					"Name": "Scored dataset",
					"EndpointType": "SasEndpoint",
					"CredentialContainer": "Inline",
					"AccessCredential": "?workspaceId=abea56e0cdb841b597321e6fe9086956&signature=WyaMkQ3YRk4YB4JRyG%2BrSuae%2FkF9%2BQe2KPNE7yYP8CQ%3D&sharedAccessUri=https%3A%2F%2Fesprodussouthsus.blob.core.windows.net%2Fexperimentoutput%2F7a46ba19-9695-40d9-89b6-5f84f9a7f4b0%2F7a46ba19-9695-40d9-89b6-5f84f9a7f4b0.dataset%3Fsv%3D2015-02-21%26sr%3Db%26sig%3DFI0PSmpLxBa9fH9q%2FAWMStyiQQNZyM0JVNEmOGRyJpk%3D%26st%3D2018-10-29T22%3A13%3A52Z%26se%3D2018-10-30T22%3A18%3A52Z%26sp%3Dr",
					"Location": "api/sharedaccess",
					"FileType": "File",
					"IsAuxiliary": false
				}
			],
			"MetadataOutputEndpoints": {
				"Scored dataset": [{
						"Key": "visualization",
						"Value": {
							"BaseUri": "https://studio.azureml.net/",
							"Size": -1,
							"Name": "Scored dataset",
							"EndpointType": "SasEndpoint",
							"CredentialContainer": "Inline",
							"AccessCredential": "?workspaceId=abea56e0cdb841b597321e6fe9086956&signature=TWHOF0g%2FxOvP%2FoFe%2BZG9q2q0r43%2Fqr0sVSJ93HNF7xI%3D&sharedAccessUri=https%3A%2F%2Fesprodussouthsus.blob.core.windows.net%2Fexperimentoutput%2F7a46ba19-9695-40d9-89b6-5f84f9a7f4b0%2Fbf804378-64c9-4b2a-ad2d-2745cbcaf088%3Fsv%3D2015-02-21%26sr%3Db%26sig%3DejQGQLeHqZ2NRVv%2F26cQoHtjIasWCkJJd%2FcBvL5Y9zg%3D%26st%3D2018-10-29T22%3A13%3A52Z%26se%3D2018-10-30T22%3A18%3A52Z%26sp%3Dr",
							"Location": "api/sharedaccess",
							"FileType": "File",
							"IsAuxiliary": false
						}
					}, {
						"Key": "schema",
						"Value": {
							"BaseUri": "https://studio.azureml.net/",
							"Size": -1,
							"Name": "Scored dataset",
							"EndpointType": "SasEndpoint",
							"CredentialContainer": "Inline",
							"AccessCredential": "?workspaceId=abea56e0cdb841b597321e6fe9086956&signature=AH2JDQHV570AyhCs0Vxny7Te%2Fc%2FH%2F8M2mUwK5CtFgs8%3D&sharedAccessUri=https%3A%2F%2Fesprodussouthsus.blob.core.windows.net%2Fexperimentoutput%2F7a46ba19-9695-40d9-89b6-5f84f9a7f4b0%2F09555500-6900-496d-bfb3-f2b14747c9e6%3Fsv%3D2015-02-21%26sr%3Db%26sig%3DlyoEDgcsRI7ElSRYgb%2B3InehYyYJqXsQM2mdEwFvkUM%3D%26st%3D2018-10-29T22%3A13%3A52Z%26se%3D2018-10-30T22%3A18%3A52Z%26sp%3Dr",
							"Location": "api/sharedaccess",
							"FileType": "File",
							"IsAuxiliary": false
						}
					}
				]
			}
		}, {
			"NodeId": "d70d4b2c-a5fa-42a5-b8dd-dd13243f0ea3-180",
			"Status": {
				"StatusCode": "Finished",
				"StatusDetail": "None",
				"CreationTime": "\/Date(1540851251859)\/",
				"StartTime": "\/Date(1540851324506)\/",
				"EndTime": "\/Date(1540851328522)\/",
				"Metadata": {
					"Evaluation results": [{
							"Name": "visualization",
							"Value": "experimentoutput/4e56ff26-1c89-4469-bda4-6fbe96908e41/dba33998-2b91-4769-8340-a12b55d6ef8a"
						}, {
							"Name": "schema",
							"Value": "experimentoutput/4e56ff26-1c89-4469-bda4-6fbe96908e41/60116c29-a3ee-48aa-9718-1f332930d86d"
						}
					]
				}
			},
			"StandardErrorEndpoint": {
				"BaseUri": "https://studio.azureml.net/",
				"Size": 90,
				"Name": "defaultSasName",
				"EndpointType": "SasEndpoint",
				"CredentialContainer": "Inline",
				"AccessCredential": "?workspaceId=abea56e0cdb841b597321e6fe9086956&signature=HMt0O6%2Ft1m8kOb7OlQfG%2By1jiUBFi35xs6xJAJEcaKM%3D&sharedAccessUri=https%3A%2F%2Fesprodussouth001.blob.core.windows.net%2Fexperimentoutput%2F0760f601-b378-455c-a9b6-ccc1631b5d01%2F0760f601-b378-455c-a9b6-ccc1631b5d01.txt%3Fsv%3D2015-02-21%26sr%3Db%26sig%3DJYJlw1Gu1f61wdp88ymmCg2T%2F0DnFsG9Umz4NdqTT4U%3D%26st%3D2018-10-29T22%3A13%3A52Z%26se%3D2018-10-30T22%3A18%3A52Z%26sp%3Dr",
				"Location": "api/sharedaccess",
				"FileType": "File",
				"IsAuxiliary": false
			},
			"StandardOutEndpoint": {
				"BaseUri": "https://studio.azureml.net/",
				"Size": 6873,
				"Name": "defaultSasName",
				"EndpointType": "SasEndpoint",
				"CredentialContainer": "Inline",
				"AccessCredential": "?workspaceId=abea56e0cdb841b597321e6fe9086956&signature=7yAquqFWc%2B5Sj4iadHgELDTqGbJOIXJ%2BUAkacJSNVfI%3D&sharedAccessUri=https%3A%2F%2Fesprodussouth001.blob.core.windows.net%2Fexperimentoutput%2Fbcad6495-37d5-4f64-bcd8-89afaa92214a%2Fbcad6495-37d5-4f64-bcd8-89afaa92214a.txt%3Fsv%3D2015-02-21%26sr%3Db%26sig%3DCjXVjHc6IukdMcEyvIqUZRzbhhnXub8fuBa22sNQD6E%3D%26st%3D2018-10-29T22%3A13%3A52Z%26se%3D2018-10-30T22%3A18%3A52Z%26sp%3Dr",
				"Location": "api/sharedaccess",
				"FileType": "File",
				"IsAuxiliary": false
			},
			"OutputEndpoints": [{
					"BaseUri": "https://studio.azureml.net/",
					"Size": 4331,
					"Name": "Evaluation results",
					"EndpointType": "SasEndpoint",
					"CredentialContainer": "Inline",
					"AccessCredential": "?workspaceId=abea56e0cdb841b597321e6fe9086956&signature=JDNMRgqy3GeJjge4NwwtIYZbI8%2B5eoHTQPyhp1GK9KM%3D&sharedAccessUri=https%3A%2F%2Fesprodussouthsus.blob.core.windows.net%2Fexperimentoutput%2F4e56ff26-1c89-4469-bda4-6fbe96908e41%2F4e56ff26-1c89-4469-bda4-6fbe96908e41.dataset%3Fsv%3D2015-02-21%26sr%3Db%26sig%3DLa9pYjSO3UbmsCFdK72Is4cT9GoAAjcZnEyqn7qc%2F0Q%3D%26st%3D2018-10-29T22%3A13%3A52Z%26se%3D2018-10-30T22%3A18%3A52Z%26sp%3Dr",
					"Location": "api/sharedaccess",
					"FileType": "File",
					"IsAuxiliary": false
				}
			],
			"MetadataOutputEndpoints": {
				"Evaluation results": [{
						"Key": "visualization",
						"Value": {
							"BaseUri": "https://studio.azureml.net/",
							"Size": -1,
							"Name": "Evaluation results",
							"EndpointType": "SasEndpoint",
							"CredentialContainer": "Inline",
							"AccessCredential": "?workspaceId=abea56e0cdb841b597321e6fe9086956&signature=xXIM4TJEn44FrOVkP5h3Ub5q0lEJnbUXEMvbsKXZX%2Bg%3D&sharedAccessUri=https%3A%2F%2Fesprodussouthsus.blob.core.windows.net%2Fexperimentoutput%2F4e56ff26-1c89-4469-bda4-6fbe96908e41%2Fdba33998-2b91-4769-8340-a12b55d6ef8a%3Fsv%3D2015-02-21%26sr%3Db%26sig%3DWPJ7V7Nd6o2%2Bumd%2B1YlppR8pMPRsxt02z%2FhblU6A8MM%3D%26st%3D2018-10-29T22%3A13%3A52Z%26se%3D2018-10-30T22%3A18%3A52Z%26sp%3Dr",
							"Location": "api/sharedaccess",
							"FileType": "File",
							"IsAuxiliary": false
						}
					}, {
						"Key": "schema",
						"Value": {
							"BaseUri": "https://studio.azureml.net/",
							"Size": -1,
							"Name": "Evaluation results",
							"EndpointType": "SasEndpoint",
							"CredentialContainer": "Inline",
							"AccessCredential": "?workspaceId=abea56e0cdb841b597321e6fe9086956&signature=L5SFBXAZAWvw7vBA159kXiC%2FhBFT8kWa42delV7opF8%3D&sharedAccessUri=https%3A%2F%2Fesprodussouthsus.blob.core.windows.net%2Fexperimentoutput%2F4e56ff26-1c89-4469-bda4-6fbe96908e41%2F60116c29-a3ee-48aa-9718-1f332930d86d%3Fsv%3D2015-02-21%26sr%3Db%26sig%3DW%2F6c%2FMo6zNq1vH0Qcdv58jlyfLCOpzq82LUMXBemNeE%3D%26st%3D2018-10-29T22%3A13%3A52Z%26se%3D2018-10-30T22%3A18%3A52Z%26sp%3Dr",
							"Location": "api/sharedaccess",
							"FileType": "File",
							"IsAuxiliary": false
						}
					}
				]
			}
		}
	],
	"Creator": "MYERSJO",
	"IsLeaf": true,
	"DisableNodesUpdate": null,
	"WebService": {
		"IsWebServiceExperiment": false,
		"Inputs": [],
		"Outputs": [],
		"Parameters": [],
		"WebServiceGroupId": null,
		"ModelPackageId": null,
		"RunId": null,
		"SerializedClientData": "<?xml version='1.0' encoding='utf-16'?><DataV1 xmlns:xsd='http://www.w3.org/2001/XMLSchema' xmlns:xsi='http://www.w3.org/2001/XMLSchema-instance'><Meta /><NodePositions></NodePositions><NodeGroups /></DataV1>",
		"ArmWebServiceId": null
	},
	"Category": "user",
	"Tags": [],
	"IsPartialRun": false
}